setup.py
setuptools_depsutil/__init__.py
setuptools_depsutil/deps_download.py
setuptools_depsutil.egg-info/PKG-INFO
setuptools_depsutil.egg-info/SOURCES.txt
setuptools_depsutil.egg-info/dependency_links.txt
setuptools_depsutil.egg-info/entry_points.txt
setuptools_depsutil.egg-info/not-zip-safe
setuptools_depsutil.egg-info/top_level.txt