Metadata-Version: 1.1
Name: setuptools-depsutil
Version: 0.0.1
Summary: setuptools command for dependency packages
Home-page: https://github.com/momijiame/setuptools-depsutil
Author: momijiame
Author-email: UNKNOWN
License: UNKNOWN
Keywords: setuptools command
Platform: UNKNOWN
Classifier: Framework :: Setuptools Plugin
Classifier: Development Status :: 4 - Beta
Classifier: Programming Language :: Python
Classifier: Intended Audience :: Developers
Classifier: Operating System :: POSIX
Classifier: Programming Language :: Python :: 2
Classifier: Programming Language :: Python :: 2.6
Classifier: Programming Language :: Python :: 2.7
Classifier: Programming Language :: Python :: 3
Classifier: Programming Language :: Python :: 3.3
Classifier: Programming Language :: Python :: 3.4
Classifier: Programming Language :: Python :: 3.5
